freamon/__init__.py
freamon/data_quality/__init__.py
freamon/data_quality/analyzer.py
freamon/data_quality/cardinality.py
freamon/data_quality/drift.py
freamon/data_quality/duplicates.py
freamon/data_quality/missing_values.py
freamon/data_quality/outliers.py
freamon/deduplication/__init__.py
freamon/deduplication/advanced_lsh.py
freamon/deduplication/auto_params.py
freamon/deduplication/blocking.py
freamon/deduplication/clustering.py
freamon/deduplication/enhanced_reporting.py
freamon/deduplication/evaluation.py
freamon/deduplication/exact_deduplication.py
freamon/deduplication/fingerprinting.py
freamon/deduplication/flag_duplicates.py
freamon/deduplication/fuzzy_deduplication.py
freamon/deduplication/lsh.py
freamon/deduplication/lsh_deduplication.py
freamon/deduplication/polars_lsh_deduplication.py
freamon/deduplication/polars_supervised_deduplication.py
freamon/deduplication/report.py
freamon/deduplication/supervised_deduplication.py
freamon/eda/__init__.py
freamon/eda/advanced_multivariate.py
freamon/eda/analyzer.py
freamon/eda/bivariate.py
freamon/eda/explainability_report.py
freamon/eda/export.py
freamon/eda/markdown_report.py
freamon/eda/multivariate.py
freamon/eda/report.py
freamon/eda/simple_report.py
freamon/eda/time_series.py
freamon/eda/univariate.py
freamon/explainability/__init__.py
freamon/explainability/shap_explainer.py
freamon/features/__init__.py
freamon/features/categorical_selection.py
freamon/features/engineer.py
freamon/features/selector.py
freamon/features/shapiq_engineer.py
freamon/features/time_series_engineer.py
freamon/imbalanced/__init__.py
freamon/integration/__init__.py
freamon/integration/allyanonimiser_bridge.py
freamon/model_selection/__init__.py
freamon/model_selection/cross_validation.py
freamon/model_selection/cv_trainer.py
freamon/model_selection/cv_training_step.py
freamon/model_selection/splitter.py
freamon/modeling/__init__.py
freamon/modeling/autoflow.py
freamon/modeling/calibration.py
freamon/modeling/early_stopping.py
freamon-0.3.57.dist-info/licenses/LICENSE
freamon-0.3.57.dist-info/METADATA
freamon-0.3.57.dist-info/WHEEL
freamon-0.3.57.dist-info/top_level.txt
freamon-0.3.57.dist-info/RECORD
