Metadata-Version: 2.4
Name: freamon
Version: 0.3.57
Summary: Advanced feature engineering, analysis, modeling and optimization for data science
Author-email: Stephen Oates <stephen.j.a.oates@gmail.com>
Classifier: Programming Language :: Python :: 3
Classifier: License :: OSI Approved :: MIT License
Classifier: Operating System :: OS Independent
Classifier: Development Status :: 4 - Beta
Classifier: Intended Audience :: Science/Research
Classifier: Topic :: Scientific/Engineering :: Artificial Intelligence
Requires-Python: >=3.10
License-File: LICENSE
Requires-Dist: numpy>=1.20.0
Requires-Dist: pandas>=1.4.0
Requires-Dist: scikit-learn>=1.0.0
Requires-Dist: matplotlib>=3.5.0
Requires-Dist: seaborn>=0.11.0
Requires-Dist: networkx>=3.0
Requires-Dist: psutil>=5.9.0
Provides-Extra: lsh
Requires-Dist: datasketch>=1.5.0; extra == "lsh"
Provides-Extra: phonetic
Requires-Dist: jellyfish>=0.9.0; extra == "phonetic"
Provides-Extra: jupyter
Requires-Dist: ipython>=8.0.0; extra == "jupyter"
Requires-Dist: ipywidgets>=8.0.0; extra == "jupyter"
Provides-Extra: enhanced-reporting
Requires-Dist: ipython>=8.0.0; extra == "enhanced-reporting"
Requires-Dist: ipywidgets>=8.0.0; extra == "enhanced-reporting"
Requires-Dist: openpyxl>=3.0.0; extra == "enhanced-reporting"
Requires-Dist: python-pptx>=0.6.0; extra == "enhanced-reporting"
Requires-Dist: plotly>=5.0.0; extra == "enhanced-reporting"
Requires-Dist: jinja2>=3.0.0; extra == "enhanced-reporting"
Requires-Dist: markdown>=3.4.0; extra == "enhanced-reporting"
Provides-Extra: dev
Requires-Dist: pytest>=7.0.0; extra == "dev"
Requires-Dist: pytest-cov>=4.0.0; extra == "dev"
Requires-Dist: black>=23.0.0; extra == "dev"
Requires-Dist: isort>=5.10.0; extra == "dev"
Requires-Dist: mypy>=1.0.0; extra == "dev"
Requires-Dist: sphinx>=6.0.0; extra == "dev"
Requires-Dist: sphinx-rtd-theme>=1.0.0; extra == "dev"
Requires-Dist: tox>=4.0.0; extra == "dev"
Requires-Dist: twine>=4.0.0; extra == "dev"
Requires-Dist: check-manifest>=0.48; extra == "dev"
Requires-Dist: pre-commit>=3.0.0; extra == "dev"
Requires-Dist: jupyter>=1.0.0; extra == "dev"
Requires-Dist: ipykernel>=6.0.0; extra == "dev"
Provides-Extra: markdown-reports
Requires-Dist: markdown>=3.4.0; extra == "markdown-reports"
Requires-Dist: networkx>=3.0; extra == "markdown-reports"
Provides-Extra: extended
Requires-Dist: polars>=0.19.0; extra == "extended"
Requires-Dist: pyarrow<15.0.0,>=12.0.0; extra == "extended"
Requires-Dist: dask>=2023.0.0; extra == "extended"
Requires-Dist: lightgbm>=4.0.0; extra == "extended"
Requires-Dist: optuna>=3.0.0; extra == "extended"
Requires-Dist: shap>=0.41.0; extra == "extended"
Requires-Dist: category_encoders>=2.5.0; extra == "extended"
Requires-Dist: openpyxl>=3.0.0; extra == "extended"
Requires-Dist: plotly>=5.0.0; extra == "extended"
Requires-Dist: jinja2>=3.0.0; extra == "extended"
Requires-Dist: statsmodels>=0.14.0; extra == "extended"
Requires-Dist: networkx>=3.0; extra == "extended"
Requires-Dist: spacy>=3.0.0; extra == "extended"
Requires-Dist: wordcloud>=1.8.0; extra == "extended"
Requires-Dist: wordfreq>=3.0.0; extra == "extended"
Requires-Dist: adjustText>=0.8; extra == "extended"
Requires-Dist: nltk>=3.8.0; extra == "extended"
Requires-Dist: textblob>=0.17.0; extra == "extended"
Provides-Extra: performance
Requires-Dist: pyarrow<15.0.0,>=12.0.0; extra == "performance"
Provides-Extra: word-embeddings
Requires-Dist: gensim>=4.0.0; extra == "word-embeddings"
Requires-Dist: scikit-learn>=1.0.0; extra == "word-embeddings"
Requires-Dist: numpy>=1.20.0; extra == "word-embeddings"
Requires-Dist: pandas>=1.4.0; extra == "word-embeddings"
Requires-Dist: matplotlib>=3.5.0; extra == "word-embeddings"
Requires-Dist: spacy>=3.0.0; extra == "word-embeddings"
Requires-Dist: nltk>=3.8.0; extra == "word-embeddings"
Provides-Extra: topic-modeling
Requires-Dist: gensim>=4.0.0; extra == "topic-modeling"
Requires-Dist: scikit-learn>=1.0.0; extra == "topic-modeling"
Requires-Dist: numpy>=1.20.0; extra == "topic-modeling"
Requires-Dist: pandas>=1.4.0; extra == "topic-modeling"
Requires-Dist: matplotlib>=3.5.0; extra == "topic-modeling"
Requires-Dist: pyldavis>=3.3.0; extra == "topic-modeling"
Requires-Dist: wordcloud>=1.8.0; extra == "topic-modeling"
Provides-Extra: all
Requires-Dist: freamon[enhanced_reporting,extended,jupyter,lsh,markdown_reports,performance,phonetic,topic_modeling,word_embeddings]; extra == "all"
Provides-Extra: full
Requires-Dist: freamon[dev,enhanced_reporting,extended,jupyter,lsh,markdown_reports,performance,phonetic,topic_modeling,word_embeddings]; extra == "full"
Dynamic: license-file
Dynamic: requires-python
